<?xml version='1.0' encoding='utf-8'?>
<TextureAtlas imagePath="luigimad.png">
<SubTexture name="luigimad idle0000" x="101" y="0" width="19" height="34" frameX="-10" frameY="-9" frameWidth="46" frameHeight="48" />
<SubTexture name="luigimad idle0001" x="50" y="0" width="25" height="38" frameX="-8" frameY="-5" frameWidth="46" frameHeight="48" />
<SubTexture name="luigimad idle0002" x="25" y="0" width="25" height="41" frameX="-7" frameY="-2" frameWidth="46" frameHeight="48" />
<SubTexture name="luigimad idle0003" x="50" y="43" width="16" height="35" frameX="-11" frameY="-8" frameWidth="46" frameHeight="48" />
<SubTexture name="luigimad down0000" x="120" y="0" width="25" height="27" frameX="-11" frameY="-18" frameWidth="46" frameHeight="48" />
<SubTexture name="luigimad down0001" x="95" y="79" width="25" height="28" frameX="-11" frameY="-16" frameWidth="46" frameHeight="48" />
<SubTexture name="luigimad down0002" x="0" y="79" width="23" height="34" frameX="-12" frameY="-10" frameWidth="46" frameHeight="48" />
<SubTexture name="luigimad left0000" x="23" y="79" width="26" height="33" frameX="-13" frameY="-12" frameWidth="46" frameHeight="48" />
<SubTexture name="luigimad left0001" x="66" y="43" width="24" height="35" frameX="-14" frameY="-10" frameWidth="46" frameHeight="48" />
<SubTexture name="luigimad left0002" x="0" y="43" width="23" height="36" frameX="-14" frameY="-9" frameWidth="46" frameHeight="48" />
<SubTexture name="luigimad right0000" x="70" y="79" width="25" height="29" frameX="-3" frameY="-8" frameWidth="30" frameHeight="43" />
<SubTexture name="luigimad right0001" x="49" y="79" width="21" height="31" frameX="-5" frameY="-6" frameWidth="30" frameHeight="43" />
<SubTexture name="luigimad up0000" x="0" y="0" width="25" height="43" frameX="-6" frameY="0" frameWidth="37" frameHeight="46" />
<SubTexture name="luigimad up0001" x="75" y="0" width="26" height="38" frameX="-6" frameY="-6" frameWidth="37" frameHeight="46" />
<SubTexture name="luigimad up0002" x="23" y="43" width="27" height="36" frameX="-5" frameY="-8" frameWidth="37" frameHeight="46" />
</TextureAtlas>
